<?xml version="1.0" encoding="UTF-8"?>
<con:soapui-project id="6226884a-049f-4dba-a183-668004f2a53d" activeEnvironment="Default" name="REST Project-user" resourceRoot="" soapui-version="5.8.0" abortOnError="false" runType="SEQUENTIAL" xmlns:con="http://eviware.com/soapui/config"><con:settings/><con:interface xsi:type="con:RestService" id="109fb423-7fd3-49ca-961a-c95438ffa7fc" wadlVersion="http://wadl.dev.java.net/2009/02" name="https://petstore.swagger.io" type="rest" xmlns:xsi="http://www.w3.org/2001/XMLSchema-instance"><con:settings/><con:definitionCache/><con:endpoints><con:endpoint>https://petstore.swagger.io</con:endpoint></con:endpoints><con:resource name="user" path="/v2/user" id="3e2c8927-5131-4aee-987a-0bd2e48c0231"><con:settings/><con:parameters/><con:method name="User Creation" id="6a4e8780-2d46-49c2-8bca-5ed01dbb9ec3" method="POST"><con:settings/><con:parameters/><con:representation type="REQUEST"><con:mediaType>application/json</con:mediaType><con:params/></con:representation><con:representation type="FAULT"><con:mediaType>text/html</con:mediaType><con:status>404</con:status><con:params/><con:element>html</con:element></con:representation><con:representation type="RESPONSE"><con:mediaType>application/json</con:mediaType><con:status>200</con:status><con:params/></con:representation><con:request name="add user" id="2683d200-24f0-4d2d-a2ae-dea89c733560" mediaType="application/json" postQueryString="false"><con:settings><con:setting id="com.eviware.soapui.impl.wsdl.WsdlRequest@request-headers">&lt;xml-fragment/></con:setting></con:settings><con:endpoint>https://petstore.swagger.io</con:endpoint><con:request>{
	"id" : 1,
	"username" : "JohnDoe",
	"firstname" : "John",
	"lastname" : "Doe",
	"email" : "john@doe.com",
	"password" : "testuser",
	"phone" : "234567890",
	"userstatus" : 0
}
</con:request><con:originalUri>https://petstore.swagger.io/https://petstore.swagger.io/v2/user</con:originalUri><con:credentials><con:authType>No Authorization</con:authType></con:credentials><con:jmsConfig JMSDeliveryMode="PERSISTENT"/><con:jmsPropertyConfig/><con:parameters/></con:request></con:method></con:resource><con:resource name="login" path="/v2/user/login" id="29caf709-16e3-4087-afa6-440b64d629e7"><con:settings/><con:parameters><con:parameter><con:name>username</con:name><con:style>TEMPLATE</con:style></con:parameter><con:parameter><con:name>password</con:name><con:style>TEMPLATE</con:style></con:parameter></con:parameters><con:method name="Method 1" id="c37b02c9-24b6-40d4-ba9d-d9d4d68867bd" method="GET"><con:settings/><con:parameters/><con:representation type="RESPONSE"><con:mediaType>application/json</con:mediaType><con:status>200</con:status><con:params/><con:element xmlns:log="https://petstore.swagger.io/v2/user/login">log:Response</con:element></con:representation><con:request name="login user" id="6e3238a9-cda9-4bf6-b5a0-a17057f93adc" mediaType="application/json"><con:settings><con:setting id="com.eviware.soapui.impl.wsdl.WsdlRequest@request-headers">&lt;xml-fragment/></con:setting></con:settings><con:endpoint>https://petstore.swagger.io</con:endpoint><con:request/><con:originalUri>https://petstore.swagger.io/v2/user/login</con:originalUri><con:credentials><con:authType>No Authorization</con:authType></con:credentials><con:jmsConfig JMSDeliveryMode="PERSISTENT"/><con:jmsPropertyConfig/><con:parameters>
  <con:entry key="password" value="testuser"/>
  <con:entry key="username" value="JOhnDoe"/>
</con:parameters><con:parameterOrder><con:entry>username</con:entry><con:entry>password</con:entry></con:parameterOrder></con:request></con:method></con:resource><con:resource name="get" path="/v2/user/{username}" id="60f0364d-12a4-4666-a09f-383d87a83fa4"><con:settings/><con:parameters><con:parameter><con:name>username</con:name><con:value>username</con:value><con:style>TEMPLATE</con:style><con:default>username</con:default></con:parameter></con:parameters><con:method name="Method 1" id="d7039ebf-9e06-4779-8718-b79f4c391ea4" method="GET"><con:settings/><con:parameters/><con:representation type="FAULT"><con:mediaType>application/json</con:mediaType><con:status>404</con:status><con:params/><con:element xmlns:ris="https://petstore.swagger.io/v2/user/rishi">ris:Fault</con:element></con:representation><con:representation type="RESPONSE"><con:mediaType>application/json</con:mediaType><con:status>200</con:status><con:params/><con:element xmlns:ris="https://petstore.swagger.io/v2/user/rishi">ris:Response</con:element></con:representation><con:representation type="REQUEST"><con:mediaType>application/json</con:mediaType><con:params/></con:representation><con:request name="get user" id="1266b622-20d4-49e8-b25d-43b2b1d5aa9b" mediaType="application/json"><con:settings><con:setting id="com.eviware.soapui.impl.wsdl.WsdlRequest@request-headers">&lt;xml-fragment/></con:setting></con:settings><con:endpoint>https://petstore.swagger.io</con:endpoint><con:request/><con:originalUri>https://petstore.swagger.io/v2/user/JohnDoe</con:originalUri><con:credentials><con:authType>No Authorization</con:authType></con:credentials><con:jmsConfig JMSDeliveryMode="PERSISTENT"/><con:jmsPropertyConfig/><con:parameters><entry key="username" value="JohnDoe" xmlns="http://eviware.com/soapui/config"/></con:parameters></con:request></con:method></con:resource><con:resource name="logout" path="/v2/user/logout" id="d3c9d86b-7177-4920-a0c0-ef43e0eb9c07"><con:settings/><con:parameters/><con:method name="Method 1" id="cfae5291-7534-464b-a658-4b65d51a861e" method="GET"><con:settings/><con:parameters/><con:representation type="RESPONSE"><con:mediaType>application/json</con:mediaType><con:status>200</con:status><con:params/><con:element xmlns:log="https://petstore.swagger.io/v2/user/logout">log:Response</con:element></con:representation><con:request name="logout user" id="5fb48315-f3fa-4b07-994a-2bdb05561ff9" mediaType="application/json"><con:settings><con:setting id="com.eviware.soapui.impl.wsdl.WsdlRequest@request-headers">&lt;xml-fragment/></con:setting></con:settings><con:endpoint>https://petstore.swagger.io</con:endpoint><con:request/><con:originalUri>https://petstore.swagger.io/v2/user/logout</con:originalUri><con:credentials><con:authType>No Authorization</con:authType></con:credentials><con:jmsConfig JMSDeliveryMode="PERSISTENT"/><con:jmsPropertyConfig/><con:parameters/></con:request></con:method></con:resource><con:resource name="delete" path="/v2/user/{username}" id="b6fe6c7f-c712-4943-a823-2a4032c6bf7a"><con:settings/><con:parameters><con:parameter><con:name>username</con:name><con:value>username</con:value><con:style>TEMPLATE</con:style><con:default>username</con:default></con:parameter></con:parameters><con:method name="Method 1" id="a5acdfaa-e0f1-4e5f-81ba-3d700921251c" method="DELETE"><con:settings/><con:parameters/><con:representation type="FAULT"><con:mediaType xsi:nil="true"/><con:status>404</con:status><con:params/><con:element>data</con:element></con:representation><con:representation type="REQUEST"><con:mediaType>application/json</con:mediaType><con:params/></con:representation><con:request name="delete user" id="f3272047-e480-411c-aa40-1c9f81587c99" mediaType="application/json" postQueryString="false"><con:settings><con:setting id="com.eviware.soapui.impl.wsdl.WsdlRequest@request-headers">&lt;xml-fragment/></con:setting></con:settings><con:endpoint>https://petstore.swagger.io</con:endpoint><con:request/><con:originalUri>https://petstore.swagger.io/v2/user/username</con:originalUri><con:credentials><con:authType>No Authorization</con:authType></con:credentials><con:jmsConfig JMSDeliveryMode="PERSISTENT"/><con:jmsPropertyConfig/><con:parameters/></con:request></con:method></con:resource></con:interface><con:testSuite id="343cb2d3-9f12-461c-bb45-f7368cc193ff" name="https://petstore.swagger.io TestSuite"><con:description>TestSuite generated for REST Service [https://petstore.swagger.io]</con:description><con:settings/><con:runType>SEQUENTIAL</con:runType><con:testCase id="9b8a0867-5f38-49f4-9cbb-db92b87f28a5" failOnError="true" failTestCaseOnErrors="true" keepSession="false" maxResults="0" name="https://petstore.swagger.io TestSuite" searchProperties="true"><con:settings/><con:testStep type="restrequest" name="user" id="895f0620-c426-40c3-a57f-27b2220837ca"><con:settings/><con:config service="https://petstore.swagger.io" resourcePath="/v2/user" methodName="User Creation" xsi:type="con:RestRequestStep" xmlns:xsi="http://www.w3.org/2001/XMLSchema-instance"><con:restRequest name="user" id="2683d200-24f0-4d2d-a2ae-dea89c733560" mediaType="application/json" postQueryString="false"><con:settings><con:setting id="com.eviware.soapui.impl.wsdl.WsdlRequest@request-headers">&lt;xml-fragment/></con:setting></con:settings><con:endpoint>https://petstore.swagger.io</con:endpoint><con:request>{
	"id" : 1,
	"username" : "JohnDoe",
	"firstname" : "John",
	"lastname" : "Doe",
	"email" : "john@doe.com",
	"password" : "testuser",
	"phone" : "234567890",
	"userstatus" : 0
}
</con:request><con:originalUri>https://petstore.swagger.io/https://petstore.swagger.io/v2/user</con:originalUri><con:credentials><con:authType>No Authorization</con:authType></con:credentials><con:jmsConfig JMSDeliveryMode="PERSISTENT"/><con:jmsPropertyConfig/><con:parameters/></con:restRequest></con:config></con:testStep><con:testStep type="restrequest" name="login" id="08ca668b-c47c-4c5e-b2b9-389cc7083f98"><con:settings/><con:config service="https://petstore.swagger.io" resourcePath="/v2/user/login" methodName="Method 1" xsi:type="con:RestRequestStep" xmlns:xsi="http://www.w3.org/2001/XMLSchema-instance"><con:restRequest name="login" id="6e3238a9-cda9-4bf6-b5a0-a17057f93adc" mediaType="application/json"><con:settings><con:setting id="com.eviware.soapui.impl.wsdl.WsdlRequest@request-headers">&lt;xml-fragment/></con:setting></con:settings><con:endpoint>https://petstore.swagger.io</con:endpoint><con:request/><con:originalUri>https://petstore.swagger.io/v2/user/login</con:originalUri><con:credentials><con:authType>No Authorization</con:authType></con:credentials><con:jmsConfig JMSDeliveryMode="PERSISTENT"/><con:jmsPropertyConfig/><con:parameters>
  <con:entry key="password" value="testuser"/>
  <con:entry key="username" value="JOhnDoe"/>
</con:parameters><con:parameterOrder><con:entry>username</con:entry><con:entry>password</con:entry></con:parameterOrder></con:restRequest></con:config></con:testStep><con:testStep type="restrequest" name="get" id="aba66cd6-d699-4494-8d87-1b4ae2ede9d2"><con:settings/><con:config service="https://petstore.swagger.io" resourcePath="/v2/user/{username}" methodName="Method 1" xsi:type="con:RestRequestStep" xmlns:xsi="http://www.w3.org/2001/XMLSchema-instance"><con:restRequest name="get" id="1266b622-20d4-49e8-b25d-43b2b1d5aa9b" mediaType="application/json"><con:settings><con:setting id="com.eviware.soapui.impl.wsdl.WsdlRequest@request-headers">&lt;xml-fragment/></con:setting></con:settings><con:endpoint>https://petstore.swagger.io</con:endpoint><con:request/><con:originalUri>https://petstore.swagger.io/v2/user/JohnDoe</con:originalUri><con:credentials><con:authType>No Authorization</con:authType></con:credentials><con:jmsConfig JMSDeliveryMode="PERSISTENT"/><con:jmsPropertyConfig/><con:parameters><entry key="username" value="JohnDoe" xmlns="http://eviware.com/soapui/config"/></con:parameters></con:restRequest></con:config></con:testStep><con:testStep type="restrequest" name="logout" id="1b0be9ef-085b-4992-96f0-0130cf9a3a60"><con:settings/><con:config service="https://petstore.swagger.io" resourcePath="/v2/user/logout" methodName="Method 1" xsi:type="con:RestRequestStep" xmlns:xsi="http://www.w3.org/2001/XMLSchema-instance"><con:restRequest name="logout" id="5fb48315-f3fa-4b07-994a-2bdb05561ff9" mediaType="application/json"><con:settings><con:setting id="com.eviware.soapui.impl.wsdl.WsdlRequest@request-headers">&lt;xml-fragment/></con:setting></con:settings><con:endpoint>https://petstore.swagger.io</con:endpoint><con:request/><con:originalUri>https://petstore.swagger.io/v2/user/logout</con:originalUri><con:credentials><con:authType>No Authorization</con:authType></con:credentials><con:jmsConfig JMSDeliveryMode="PERSISTENT"/><con:jmsPropertyConfig/><con:parameters/></con:restRequest></con:config></con:testStep><con:testStep type="restrequest" name="delete" id="04b68070-83a4-487b-afe6-0f6829f7e052"><con:settings/><con:config service="https://petstore.swagger.io" resourcePath="/v2/user/{username}" methodName="Method 1" xsi:type="con:RestRequestStep" xmlns:xsi="http://www.w3.org/2001/XMLSchema-instance"><con:restRequest name="delete" id="f3272047-e480-411c-aa40-1c9f81587c99" mediaType="application/json" postQueryString="false"><con:settings><con:setting id="com.eviware.soapui.impl.wsdl.WsdlRequest@request-headers">&lt;xml-fragment/></con:setting></con:settings><con:endpoint>https://petstore.swagger.io</con:endpoint><con:request/><con:originalUri>https://petstore.swagger.io/v2/user/JohnDoe</con:originalUri><con:credentials><con:authType>No Authorization</con:authType></con:credentials><con:jmsConfig JMSDeliveryMode="PERSISTENT"/><con:jmsPropertyConfig/><con:parameters><entry key="username" value="JohnDoe" xmlns="http://eviware.com/soapui/config"/></con:parameters></con:restRequest></con:config></con:testStep><con:properties/></con:testCase><con:properties/></con:testSuite><con:properties/><con:wssContainer/><con:oAuth2ProfileContainer/><con:oAuth1ProfileContainer/><con:sensitiveInformation/></con:soapui-project>